cvehunter/Connect.py
cvehunter/Cve.py
cvehunter/Cvss.py
cvehunter/__init__.py
cvehunter/cvehunter.py
cvehunter/utils.py
cvehunter-1.0.6.dist-info/LICENSE
cvehunter-1.0.6.dist-info/METADATA
cvehunter-1.0.6.dist-info/WHEEL
cvehunter-1.0.6.dist-info/top_level.txt
cvehunter-1.0.6.dist-info/RECORD
