Metadata-Version: 2.1
Name: cvehunter
Version: 1.0.6
Summary: Asynchronous python wrapper for the NVD API
Home-page: https://github.com/Xample33/cvehunter
Author: Xample33
Maintainer: Xample33
License: MIT
Keywords: cve nist nvd cpe cwe cvss vulnerability api
Classifier: Development Status :: 5 - Production/Stable
Classifier: Programming Language :: Python
Classifier: Programming Language :: Python :: 3
Classifier: Programming Language :: Python :: 3.9
Classifier: Programming Language :: Python :: 3.10
Classifier: Programming Language :: Python :: 3.11
Classifier: Operating System :: OS Independent
Requires-Python: >=3.9
License-File: LICENSE
Requires-Dist: httpx
Requires-Dist: urllib3
